bulkimgconvert/__init__.py
bulkimgconvert/converter.py
bulkimgconvert/main.py
bulkimgconvert-1.0.0.dist-info/licenses/LICENSE
bulkimgconvert-1.0.0.dist-info/METADATA
bulkimgconvert-1.0.0.dist-info/WHEEL
bulkimgconvert-1.0.0.dist-info/entry_points.txt
bulkimgconvert-1.0.0.dist-info/top_level.txt
bulkimgconvert-1.0.0.dist-info/RECORD
