Metadata-Version: 2.4
Name: bulkimgconvert
Version: 1.0.0
Summary: A simple bulk image converter
Author: Navneet Kaur
Author-email: Navneet Kaur <navi24493@gmail.com>
License: MIT
Requires-Python: >=3.6
License-File: LICENSE
Requires-Dist: Pillow
Requires-Dist: tqdm
Dynamic: author
Dynamic: license-file
Dynamic: requires-python
